trysoma_sdk_core-0.0.6.dist-info/METADATA
trysoma_sdk_core-0.0.6.dist-info/WHEEL
trysoma_sdk_core/__init__.py
trysoma_sdk_core/__init__.pyi
trysoma_sdk_core/py.typed
trysoma_sdk_core/trysoma_sdk_core.abi3.so
trysoma_sdk_core-0.0.6.dist-info/RECORD
