Metadata-Version: 2.4
Name: trysoma_sdk_core
Version: 0.0.6
Classifier: Development Status :: 3 - Alpha
Classifier: Intended Audience :: Developers
Classifier: License :: OSI Approved :: MIT License
Classifier: Programming Language :: Python :: 3
Classifier: Programming Language :: Python :: 3.10
Classifier: Programming Language :: Python :: 3.11
Classifier: Programming Language :: Python :: 3.12
Classifier: Programming Language :: Python :: 3.13
Classifier: Programming Language :: Rust
Classifier: Programming Language :: Python :: Implementation :: CPython
Summary: Core native bindings for the Soma Python SDK
Keywords: soma,sdk,agent,ai
License-Expression: MIT
Requires-Python: >=3.10
Project-URL: Homepage, https://github.com/trysoma/soma
Project-URL: Repository, https://github.com/trysoma/soma
